explicitor/__init__.py
explicitor/decorators.py
explicitor/types/__init__.py
explicitor/types/result.py
explicitor/utils.py
explicitor-0.1.0.dist-info/LICENSE
explicitor-0.1.0.dist-info/WHEEL
explicitor-0.1.0.dist-info/METADATA
explicitor-0.1.0.dist-info/RECORD
