Metadata-Version: 2.1
Name: explicitor
Version: 0.1.0
Summary: Rust-like explicit error handling for typed Python
Home-page: https://github.com/din14970/explicitor
License: MIT
Keywords: typing,error handling,rust
Author: Niels Cautaerts
Author-email: nielscautaerts@hotmail.com
Requires-Python: >=3.10,<4.0
Classifier: License :: OSI Approved :: MIT License
Classifier: Programming Language :: Python :: 3
Classifier: Programming Language :: Python :: 3.10
Classifier: Programming Language :: Python :: 3.11
Project-URL: Repository, https://github.com/din14970/explicitor
